sparseqr/__init__.py
sparseqr/cffi_asarray.py
sparseqr/sparseqr.py
sparseqr/sparseqr_gen.py
sparseqr-1.1.0.dist-info/LICENSE.md
sparseqr-1.1.0.dist-info/WHEEL
sparseqr-1.1.0.dist-info/METADATA
sparseqr-1.1.0.dist-info/RECORD
