Metadata-Version: 2.1
Name: sparseqr
Version: 1.1.0
Summary: Python wrapper for SuiteSparseQR
License: Public Domain CC0
Author: Yotam Gingold
Author-email: yotam@yotamgingold.com> and Juha Jeronen <juha.jeronen@tut.fi
Requires-Python: >=3.7,<4.0
Classifier: License :: Other/Proprietary License
Classifier: Programming Language :: Python :: 3
Classifier: Programming Language :: Python :: 3.7
Classifier: Programming Language :: Python :: 3.8
Classifier: Programming Language :: Python :: 3.9
Requires-Dist: cffi (>=1.0,<2.0)
Requires-Dist: numpy (>=1.21,<2.0)
Requires-Dist: scipy (>=1.0,<2.0)
